Metadata-Version: 1.1
Name: get-template
Version: 1.0.4
Summary: Templating
Home-page: https://gitlab.com/Dithyrambe/templator
Author: dithyrambe
Author-email: dithyrambe@outlook.fr
License: WTFPL
Keywords: Template
Platform: UNKNOWN
Classifier: Programming Language :: Python :: 3
Classifier: Programming Language :: Python :: 3.3
Classifier: Programming Language :: Python :: 3.4
Classifier: Programming Language :: Python :: 3.5
Classifier: Programming Language :: Python :: 3.6
